spectpsftoolbox/kernel1d.py
spectpsftoolbox/kernel2d.py
spectpsftoolbox/operator2d.py
spectpsftoolbox/simind_io.py
spectpsftoolbox/utils.py
spectpsftoolbox-0.1.2.dist-info/METADATA
spectpsftoolbox-0.1.2.dist-info/WHEEL
spectpsftoolbox-0.1.2.dist-info/licenses/LICENSE
spectpsftoolbox-0.1.2.dist-info/RECORD
