Metadata-Version: 2.4
Name: spectpsftoolbox
Version: 0.1.2
Summary: Library for creation of point spread functions
Project-URL: Homepage, https://github.com/qurit/SPECTPSFToolbox
Project-URL: Bug Tracker, https://github.com/qurit/SPECTPSFToolbox/issues
Author-email: Luke Polson <lukepolson@outlook.com>
License-File: LICENSE
Classifier: License :: OSI Approved :: MIT License
Classifier: Operating System :: OS Independent
Classifier: Programming Language :: Python :: 3
Requires-Python: >=3.9
Requires-Dist: dill==0.3.9
Requires-Dist: fft-conv-pytorch>=1.2.0
Requires-Dist: numpy>=1.24.2
Requires-Dist: torch>=1.10.2
Requires-Dist: torchquad==0.4.1
Requires-Dist: torchvision==0.20.1
Provides-Extra: doc
Requires-Dist: furo; extra == 'doc'
Requires-Dist: ipykernel; extra == 'doc'
Requires-Dist: myst-parser; extra == 'doc'
Requires-Dist: nbsphinx; extra == 'doc'
Requires-Dist: pydata-sphinx-theme; extra == 'doc'
Requires-Dist: sphinx-autoapi~=3.0.0; extra == 'doc'
Requires-Dist: sphinx-design; extra == 'doc'
Requires-Dist: sphinx~=6.2.1; extra == 'doc'
Requires-Dist: toml; extra == 'doc'
